{
  "annotations": {
    "changelogDate": "20250317004644"
  },
  "applications": "*",
  "dto": "mapstruct",
  "fields": [
    {
      "fieldName": "nota",
      "fieldType": "Integer",
      "fieldValidateRules": ["required"]
    },
    {
      "fieldName": "materia",
      "fieldType": "AreaDoEnem",
      "fieldValidateRules": ["required"],
      "fieldValues": "LINGUAGENS,CODIGOS,CIENCIAS_HUMANAS,CIENCIAS_NATUREZA,MATEMATICA"
    }
  ],
  "name": "Meta",
  "pagination": "pagination",
  "relationships": [
    {
      "otherEntityName": "aluno",
      "otherEntityRelationshipName": "meta",
      "relationshipName": "aluno",
      "relationshipSide": "right",
      "relationshipType": "many-to-one",
      "relationshipValidateRules": "required"
    }
  ],
  "searchEngine": "no",
  "service": "serviceClass"
}
